cursor_mcp_manager/__init__.py
cursor_mcp_manager/__main__.py
cursor_mcp_manager/active_log_collector.py
cursor_mcp_manager/manager_cli.py
cursor_mcp_manager/process_monitor.py
cursor_mcp_manager/process_watcher.py
cursor_mcp_manager/server.py
cursor_mcp_manager/stdio_proxy.py
cursor_mcp-0.1.1.dist-info/METADATA
cursor_mcp-0.1.1.dist-info/WHEEL
cursor_mcp-0.1.1.dist-info/entry_points.txt
cursor_mcp-0.1.1.dist-info/licenses/LICENSE
cursor_mcp-0.1.1.dist-info/RECORD
