Metadata-Version: 2.4
Name: cursor-mcp
Version: 0.1.1
Summary: MCP server for managing Cursor IDE MCP configurations
Project-URL: Homepage, https://github.com/hud-evals/hud-cursor-manager
Project-URL: Bug Tracker, https://github.com/hud-evals/hud-cursor-manager/issues
Project-URL: Documentation, https://github.com/hud-evals/hud-cursor-manager/tree/main/README.md
Author-email: lorenss-m <saeclmusic@gmail.com>
License: MIT License
License-File: LICENSE
Keywords: cursor,ide,mcp,modelcontextprotocol
Classifier: Development Status :: 3 - Alpha
Classifier: Intended Audience :: Developers
Classifier: License :: OSI Approved :: MIT License
Classifier: Programming Language :: Python :: 3
Classifier: Programming Language :: Python :: 3.10
Classifier: Programming Language :: Python :: 3.11
Classifier: Programming Language :: Python :: 3.12
Requires-Python: >=3.10
Requires-Dist: click>=8.0.0
Requires-Dist: fastmcp>=2.11.0
Requires-Dist: httpx>=0.24.0
Requires-Dist: mcp[cli]>=1.12.3
Requires-Dist: psutil>=5.9.0
